.DS_Store
opusminer/.DS_Store
opusminer/OpusMiner.py
opusminer/__init__.py
opusminer/Sample/TestOpusMiner.py
opusminer/Sample/__init__.py
opusminer/cpplib/__init__.py
opusminer/cpplib/boostpython2/__init__.py
opusminer/cpplib/boostpython3/__init__.py
opusminer-1.2.0.dist-info/DESCRIPTION.rst
opusminer-1.2.0.dist-info/METADATA
opusminer-1.2.0.dist-info/RECORD
opusminer-1.2.0.dist-info/WHEEL
opusminer-1.2.0.dist-info/metadata.json
opusminer-1.2.0.dist-info/top_level.txt
