Metadata-Version: 2.0
Name: opusminer
Version: 1.2.0
Summary: The Python project that implements the Opus algorithm
Home-page: https://github.com/situsnow/opusminer
Author: Geoff.I.Webb
Author-email: Geoff.Webb@monash.edu
License: GNU
Platform: UNKNOWN
Requires-Python: >=2
Requires-Dist: pandas
Requires-Dist: numpy
